p2api/__about__.py
p2api/__init__.py
p2api/p2api.py
p2api/utils/__init__.py
p2api/utils/eso_period.py
p2api/utils/generate_finding_charts.py
p2api/utils/p2api_utils.py
p2api-1.0.10.dist-info/METADATA
p2api-1.0.10.dist-info/WHEEL
p2api-1.0.10.dist-info/entry_points.txt
p2api-1.0.10.dist-info/licenses/LICENSE
p2api-1.0.10.dist-info/RECORD
