Metadata-Version: 2.3
Name: p2api
Version: 1.0.10
Summary: Binding for the ESO phase 2 programmatic API
Project-URL: Homepage, https://www.eso.org/copdemo/apidoc/index.html
Author-email: Thomas Bierwirth <thomas.bierwirth@eso.org>, John Pritchard <john.pritchard@eso.org>
License: MIT License
License-File: LICENSE
Keywords: API,ESO,Observation,Phase2,Preparation,Programmatic
Classifier: Development Status :: 5 - Production/Stable
Classifier: Intended Audience :: Developers
Classifier: License :: OSI Approved :: MIT License
Classifier: Programming Language :: Python :: 3
Classifier: Programming Language :: Python :: 3.4
Classifier: Programming Language :: Python :: 3.5
Classifier: Programming Language :: Python :: 3.6
Classifier: Programming Language :: Python :: 3.7
Classifier: Programming Language :: Python :: 3.8
Classifier: Programming Language :: Python :: 3.9
Classifier: Programming Language :: Python :: 3.10
Classifier: Programming Language :: Python :: 3.11
Classifier: Programming Language :: Python :: 3.12
Requires-Dist: keyring
Requires-Dist: requests
